mavedb/__init__.py
mavedb/constants.py
mavedb/data_providers/services.py
mavedb/db/athena.py
mavedb/db/base.py
mavedb/db/session.py
mavedb/db/view.py
mavedb/deps.py
mavedb/lib/acmg.py
mavedb/lib/annotation/__init__.py
mavedb/lib/annotation/agent.py
mavedb/lib/annotation/annotate.py
mavedb/lib/annotation/classification.py
mavedb/lib/annotation/condition.py
mavedb/lib/annotation/constants.py
mavedb/lib/annotation/contribution.py
mavedb/lib/annotation/dataset.py
mavedb/lib/annotation/document.py
mavedb/lib/annotation/evidence_line.py
mavedb/lib/annotation/exceptions.py
mavedb/lib/annotation/method.py
mavedb/lib/annotation/proposition.py
mavedb/lib/annotation/py.typed
mavedb/lib/annotation/statement.py
mavedb/lib/annotation/study_result.py
mavedb/lib/annotation/util.py
mavedb/lib/authentication.py
mavedb/lib/authorization.py
mavedb/lib/clingen/__init__.py
mavedb/lib/clingen/allele_registry.py
mavedb/lib/clingen/constants.py
mavedb/lib/clingen/content_constructors.py
mavedb/lib/clingen/py.typed
mavedb/lib/clingen/services.py
mavedb/lib/contributors.py
mavedb/lib/exceptions.py
mavedb/lib/experiments.py
mavedb/lib/external_publications.py
mavedb/lib/gnomad.py
mavedb/lib/identifiers.py
mavedb/lib/keywords.py
mavedb/lib/logging/__init__.py
mavedb/lib/logging/canonical.py
mavedb/lib/logging/context.py
mavedb/lib/logging/logged_route.py
mavedb/lib/logging/models.py
mavedb/lib/mapping.py
mavedb/lib/mave/constants.py
mavedb/lib/mave/hgvs.py
mavedb/lib/mave/utils.py
mavedb/lib/mave/variant.py
mavedb/lib/oddspaths.py
mavedb/lib/orcid.py
mavedb/lib/permissions.py
mavedb/lib/score_calibrations.py
mavedb/lib/score_sets.py
mavedb/lib/seqrepo.py
mavedb/lib/slack.py
mavedb/lib/target_genes.py
mavedb/lib/taxonomies.py
mavedb/lib/temp_urns.py
mavedb/lib/types/__init__.py
mavedb/lib/types/annotation.py
mavedb/lib/types/clingen.py
mavedb/lib/types/uniprot.py
mavedb/lib/uniprot/__init__.py
mavedb/lib/uniprot/constants.py
mavedb/lib/uniprot/id_mapping.py
mavedb/lib/uniprot/py.typed
mavedb-2025.5.0.dist-info/METADATA
mavedb-2025.5.0.dist-info/WHEEL
mavedb-2025.5.0.dist-info/licenses/LICENSE
mavedb-2025.5.0.dist-info/RECORD
