Metadata-Version: 2.4
Name: mavedb
Version: 2025.5.0
Summary: API for MaveDB, the database of Multiplexed Assays of Variant Effect.
License: AGPL-3.0-only
License-File: LICENSE
Requires-Python: >=3.11,<4.0
Classifier: Development Status :: 3 - Alpha
Classifier: Intended Audience :: Science/Research
Classifier: License :: OSI Approved :: GNU Affero General Public License v3
Classifier: Operating System :: OS Independent
Classifier: Programming Language :: Python :: 3
Classifier: Programming Language :: Python :: 3.11
Classifier: Programming Language :: Python :: 3.12
Classifier: Programming Language :: Python :: 3.13
Classifier: Programming Language :: Python :: 3.14
Classifier: Topic :: Scientific/Engineering :: Bio-Informatics
Provides-Extra: server
Requires-Dist: IDUtils (>=1.2.0,<1.3.0)
Requires-Dist: SQLAlchemy (>=2.0.29,<2.1.0)
Requires-Dist: alembic (>=1.14.0,<1.15.0) ; extra == "server"
Requires-Dist: alembic-utils (==0.8.1) ; extra == "server"
Requires-Dist: arq (>=0.25.0,<0.26.0) ; extra == "server"
Requires-Dist: authlib (>=1.6.5,<1.7.0) ; extra == "server"
Requires-Dist: biocommons (>=0.0.0,<0.1.0) ; extra == "server"
Requires-Dist: boto3 (>=1.34.97,<1.35.0) ; extra == "server"
Requires-Dist: cdot (>=0.2.21,<0.3.0) ; extra == "server"
Requires-Dist: cryptography (>=44.0.1,<44.1.0) ; extra == "server"
Requires-Dist: email_validator (>=2.1.1,<2.2.0)
Requires-Dist: eutils (>=0.6.0,<0.7.0)
Requires-Dist: fastapi (>=0.121.0,<0.122.0) ; extra == "server"
Requires-Dist: fqfa (>=1.3.0,<1.4.0)
Requires-Dist: ga4gh-va-spec (>=0.4.2,<0.5.0) ; extra == "server"
Requires-Dist: hgvs (>=1.5.4,<1.6.0) ; extra == "server"
Requires-Dist: httpx (>=0.26.0,<0.27.0)
Requires-Dist: mavehgvs (>=0.7.0,<0.8.0)
Requires-Dist: numpy (>=1.26,<1.27)
Requires-Dist: orcid (>=1.0.3,<1.1.0) ; extra == "server"
Requires-Dist: pandas (>=1.4.1,<1.5.0)
Requires-Dist: psycopg2 (>=2.9.3,<2.10.0) ; extra == "server"
Requires-Dist: pyathena (>=3.14.1,<3.15.0) ; extra == "server"
Requires-Dist: pydantic (>=2.10.0,<2.11.0)
Requires-Dist: pyhumps (>=3.8.0,<3.9.0)
Requires-Dist: python-dotenv (>=0.20.0,<0.21.0)
Requires-Dist: python-jose[cryptography] (>=3.5.0,<3.6.0) ; extra == "server"
Requires-Dist: python-json-logger (>=2.0.7,<2.1.0)
Requires-Dist: python-multipart (>=0.0.5,<0.1.0) ; extra == "server"
Requires-Dist: pyyaml (>=6.0.1,<6.1.0)
Requires-Dist: requests (>=2.32.2,<2.33.0) ; extra == "server"
Requires-Dist: slack-sdk (>=3.21.3,<3.22.0) ; extra == "server"
Requires-Dist: starlette (>=0.49.0,<0.50.0) ; extra == "server"
Requires-Dist: starlette-context (>=0.3.6,<0.4.0) ; extra == "server"
Requires-Dist: uvicorn[standard] ; extra == "server"
Requires-Dist: watchtower (>=3.2.0,<3.3.0) ; extra == "server"
Project-URL: Documentation, https://mavedb.org/docs/mavedb/
Project-URL: Homepage, https://mavedb.org
Project-URL: Repository, https://github.com/VariantEffect/mavedb-api
